jupyter_kernel_mgmt/__init__.py
jupyter_kernel_mgmt/_version.py
jupyter_kernel_mgmt/client.py
jupyter_kernel_mgmt/client_base.py
jupyter_kernel_mgmt/discovery.py
jupyter_kernel_mgmt/hl.py
jupyter_kernel_mgmt/kernelapp.py
jupyter_kernel_mgmt/kernelspec.py
jupyter_kernel_mgmt/localinterfaces.py
jupyter_kernel_mgmt/managerabc.py
jupyter_kernel_mgmt/nanny.py
jupyter_kernel_mgmt/restarter.py
jupyter_kernel_mgmt/util.py
jupyter_kernel_mgmt/subproc/__init__.py
jupyter_kernel_mgmt/subproc/launcher.py
jupyter_kernel_mgmt/subproc/manager.py
jupyter_kernel_mgmt/subproc/win_interrupt.py
jupyter_kernel_mgmt/tests/__init__.py
jupyter_kernel_mgmt/tests/conftest.py
jupyter_kernel_mgmt/tests/signalkernel.py
jupyter_kernel_mgmt/tests/test_async_manager.py
jupyter_kernel_mgmt/tests/test_client_blocking.py
jupyter_kernel_mgmt/tests/test_client_loop.py
jupyter_kernel_mgmt/tests/test_discovery.py
jupyter_kernel_mgmt/tests/test_kernelapp.py
jupyter_kernel_mgmt/tests/test_kernelspec.py
jupyter_kernel_mgmt/tests/test_localinterfaces.py
jupyter_kernel_mgmt/tests/test_manager.py
jupyter_kernel_mgmt/tests/test_restarter.py
jupyter_kernel_mgmt/tests/utils.py
jupyter_kernel_mgmt-0.5.1.dist-info/COPYING.md
jupyter_kernel_mgmt-0.5.1.dist-info/METADATA
jupyter_kernel_mgmt-0.5.1.dist-info/WHEEL
jupyter_kernel_mgmt-0.5.1.dist-info/entry_points.txt
jupyter_kernel_mgmt-0.5.1.dist-info/top_level.txt
jupyter_kernel_mgmt-0.5.1.dist-info/RECORD
